kaldo/.DS_Store
kaldo/__init__.py
kaldo/_version.py
kaldo/conductivity.py
kaldo/forceconstants.py
kaldo/grid.py
kaldo/phonons.py
kaldo/quasiharmonic.py
kaldo/storable.py
kaldo/.idea/.gitignore
kaldo/.idea/kaldo.iml
kaldo/.idea/misc.xml
kaldo/.idea/modules.xml
kaldo/.idea/vcs.xml
kaldo/.idea/workspace.xml
kaldo/.idea/inspectionProfiles/Project_Default.xml
kaldo/.idea/inspectionProfiles/profiles_settings.xml
kaldo/controllers/__init__.py
kaldo/controllers/anharmonic.py
kaldo/controllers/dirac_kernel.py
kaldo/controllers/displacement.py
kaldo/controllers/isotopic.py
kaldo/controllers/kaldo_style_guide.mpl
kaldo/controllers/legacy_dataset.json
kaldo/controllers/plotter.py
kaldo/controllers/sigma2.py
kaldo/helpers/__init__.py
kaldo/helpers/logger.py
kaldo/helpers/tools.py
kaldo/interfaces/__init__.py
kaldo/interfaces/eskm_io.py
kaldo/interfaces/hiphive_io.py
kaldo/interfaces/shengbte_io.py
kaldo/interfaces/tdep_io.py
kaldo/observables/__init__.py
kaldo/observables/forceconstant.py
kaldo/observables/harmonic_with_q.py
kaldo/observables/harmonic_with_q_temp.py
kaldo/observables/observable.py
kaldo/observables/secondorder.py
kaldo/observables/thirdorder.py
kaldo/tests/.DS_Store
kaldo/tests/__init__.py
kaldo/tests/test_amorphous_af_conductivity.py
kaldo/tests/test_amorphous_classic.py
kaldo/tests/test_amorphous_quantum.py
kaldo/tests/test_antiresonant.py
kaldo/tests/test_broadening_shapes_amorphous.py
kaldo/tests/test_broadening_shapes_crystal.py
kaldo/tests/test_crystal.py
kaldo/tests/test_crystal_d3q.py
kaldo/tests/test_crystal_finite_size_np.py
kaldo/tests/test_crystal_free_energy.py
kaldo/tests/test_crystal_is_unfolding.py
kaldo/tests/test_crystal_is_unfolding_qe.py
kaldo/tests/test_crystal_isotopic.py
kaldo/tests/test_crystal_qe_vasp.py
kaldo/tests/test_crystal_vasp.py
kaldo/tests/test_crystal_vasp_d3q.py
kaldo/tests/test_detailed_balance.py
kaldo/tests/test_diffusivity.py
kaldo/tests/test_elastic.py
kaldo/tests/test_elastic_qe.py
kaldo/tests/test_elastic_vasp.py
kaldo-2.0.4.dist-info/licenses/LICENSE
kaldo-2.0.4.dist-info/METADATA
kaldo-2.0.4.dist-info/WHEEL
kaldo-2.0.4.dist-info/top_level.txt
kaldo-2.0.4.dist-info/RECORD
