Metadata-Version: 2.4
Name: kaldo
Version: 2.0.4
Author: kaldo Developers
Author-email: gbarbalinardo@ucdavis.edu
License: BSD-3-Clause
License-File: LICENSE
Requires-Dist: numpy>=1.25.1
Requires-Dist: scipy>=1.11.1
Requires-Dist: ase>=3.22.1
Requires-Dist: sparse>=0.15
Requires-Dist: seekpath>=1.8
Requires-Dist: tensorflow>=2.13
Requires-Dist: opt_einsum>=2.3
Requires-Dist: scikit-learn>=1.3.0
Requires-Dist: h5py>=3.9.0
Requires-Dist: pandas>=2.0.3
Requires-Dist: codecov>=2.1.7
Requires-Dist: pytest-cov>=2.10.0
Requires-Dist: pytest>=5.2.1
Requires-Dist: psutil>=5.7.2
Requires-Dist: hiphive>=1.1
Dynamic: author
Dynamic: author-email
Dynamic: description
Dynamic: description-content-type
Dynamic: license
Dynamic: license-file
Dynamic: requires-dist
